sentry_plugins/__init__.py
sentry_plugins/anonymizeip.py
sentry_plugins/assets.json
sentry_plugins/base.py
sentry_plugins/client.py
sentry_plugins/constants.py
sentry_plugins/exceptions.py
sentry_plugins/utils.py
sentry_plugins/amazon_sqs/__init__.py
sentry_plugins/amazon_sqs/plugin.py
sentry_plugins/asana/__init__.py
sentry_plugins/asana/client.py
sentry_plugins/asana/plugin.py
sentry_plugins/bitbucket/__init__.py
sentry_plugins/bitbucket/client.py
sentry_plugins/bitbucket/mixins.py
sentry_plugins/bitbucket/plugin.py
sentry_plugins/bitbucket/repository_provider.py
sentry_plugins/bitbucket/testutils.py
sentry_plugins/bitbucket/urls.py
sentry_plugins/bitbucket/endpoints/__init__.py
sentry_plugins/bitbucket/endpoints/webhook.py
sentry_plugins/clubhouse/__init__.py
sentry_plugins/clubhouse/client.py
sentry_plugins/clubhouse/plugin.py
sentry_plugins/github/__init__.py
sentry_plugins/github/client.py
sentry_plugins/github/options.py
sentry_plugins/github/plugin.py
sentry_plugins/github/testutils.py
sentry_plugins/github/urls.py
sentry_plugins/github/endpoints/__init__.py
sentry_plugins/github/endpoints/webhook.py
sentry_plugins/gitlab/__init__.py
sentry_plugins/gitlab/client.py
sentry_plugins/gitlab/endpoints.py
sentry_plugins/gitlab/plugin.py
sentry_plugins/heroku/__init__.py
sentry_plugins/heroku/plugin.py
sentry_plugins/hipchat_ac/__init__.py
sentry_plugins/hipchat_ac/cards.py
sentry_plugins/hipchat_ac/mentions.py
sentry_plugins/hipchat_ac/models.py
sentry_plugins/hipchat_ac/plugin.py
sentry_plugins/hipchat_ac/testutils.py
sentry_plugins/hipchat_ac/urls.py
sentry_plugins/hipchat_ac/utils.py
sentry_plugins/hipchat_ac/views.py
sentry_plugins/hipchat_ac/endpoints/__init__.py
sentry_plugins/hipchat_ac/endpoints/tenants.py
sentry_plugins/hipchat_ac/endpoints/test_config.py
sentry_plugins/hipchat_ac/south_migrations/0001_initial.py
sentry_plugins/hipchat_ac/south_migrations/0002_auto__del_mentionedevent.py
sentry_plugins/hipchat_ac/south_migrations/__init__.py
sentry_plugins-9.1.2.dist-info/LICENSE
sentry_plugins-9.1.2.dist-info/METADATA
sentry_plugins-9.1.2.dist-info/WHEEL
sentry_plugins-9.1.2.dist-info/entry_points.txt
sentry_plugins-9.1.2.dist-info/top_level.txt
sentry_plugins-9.1.2.dist-info/RECORD
